{
  "curl": {
    "id": "curl",
    "description": "",
    "name": "cURL",
    "type": "tool",
    "dependencies": [
      "graphql",
      "rest"
    ],
    "resources": {
      "articles": [],
      "books": [],
      "courses": [],
      "documentation": [],
      "videos": []
    }
  },
  "postman": {
    "id": "postman",
    "description": "",
    "name": "Postman",
    "type": "tool",
    "dependencies": [
      "graphql",
      "rest"
    ],
    "resources": {
      "articles": [],
      "books": [],
      "courses": [],
      "documentation": [],
      "videos": []
    }
  },
  "less": {
    "id": "less",
    "description": "",
    "name": "Less",
    "type": "tool",
    "dependencies": [
      "css"
    ],
    "resources": {
      "articles": [],
      "books": [],
      "courses": [],
      "documentation": [],
      "videos": []
    }
  },
  "sass": {
    "id": "sass",
    "description": "",
    "name": "Sass",
    "type": "tool",
    "dependencies": [
      "css"
    ],
    "resources": {
      "articles": [],
      "books": [],
      "courses": [],
      "documentation": [],
      "videos": []
    }
  },
  "vite": {
    "id": "vite",
    "description": "",
    "name": "Vite",
    "type": "tool",
    "dependencies": [
      "javascript"
    ],
    "resources": {
      "articles": [],
      "books": [],
      "courses": [],
      "documentation": [],
      "videos": []
    }
  },
  "docker": {
    "id": "docker",
    "description": "",
    "name": "Docker",
    "type": "tool",
    "dependencies": [
      "devops"
    ],
    "resources": {
      "articles": [],
      "books": [],
      "courses": [],
      "documentation": [],
      "videos": []
    }
  },
  "kubernetes": {
    "id": "kubernetes",
    "description": "",
    "name": "Kubernetes",
    "type": "tool",
    "dependencies": [
      "devops"
    ],
    "resources": {
      "articles": [],
      "books": [],
      "courses": [],
      "documentation": [],
      "videos": []
    }
  },
  "terraform": {
    "id": "terraform",
    "description": "",
    "name": "Terraform",
    "type": "tool",
    "dependencies": [
      "devops"
    ],
    "resources": {
      "articles": [],
      "books": [],
      "courses": [],
      "documentation": [],
      "videos": []
    }
  },
  "npm": {
    "id": "npm",
    "description": "",
    "name": "NPM",
    "type": "tool",
    "dependencies": [
      "nodejs"
    ],
    "resources": {
      "articles": [],
      "books": [],
      "courses": [],
      "documentation": [],
      "videos": []
    }
  },
  "yarn": {
    "id": "yarn",
    "description": "",
    "name": "Yarn",
    "type": "tool",
    "dependencies": [
      "nodejs"
    ],
    "resources": {
      "articles": [],
      "books": [],
      "courses": [],
      "documentation": [],
      "videos": []
    }
  }
}